clcache/__init__.py
clcache/__main__.py
clcache/monkey.py
clcache/storage.py
clcache/server/__init__.py
clcache/server/__main__.py
clcache-4.2.0.data/data/clcache.pth
clcache-4.2.0.dist-info/METADATA
clcache-4.2.0.dist-info/RECORD
clcache-4.2.0.dist-info/WHEEL
clcache-4.2.0.dist-info/entry_points.txt
clcache-4.2.0.dist-info/top_level.txt
